Workbook

Sheet Listas_aux
A1: ocupacao | B1: banco | C1: parentesco | D1: tipo_rend | E1: categoria | F1: grupo_bem | G1: tipo_divida
A2: Aposentado(a) | B2: Banco do Brasil | C2: Filho(a) | D2: Tributável | E2: Despesas médicas | F2: Imóveis | G2: Empréstimo bancário
A3: Autônomo(a) | B3: Caixa Econômica Federal | C3: Enteado(a) | D3: Isento e não tributável | E3: Plano de saúde | F3: Veículos | G3: Financiamento imobiliário
A4: Empregado(a) CLT | B4: Bradesco | C4: Cônjuge/companheiro(a) | D4: Tributação exclusiva/definitiva | E4: Educação | F4: Contas e dinheiro | G4: Financiamento de veículo
A5: Empresário(a)/Sócio(a) | B5: Itaú | C5: Pai | E5: Previdência oficial (INSS) | F5: Aplicações e investimentos | G5: Cartão de crédito
A6: Estudante | B6: Santander | C6: Mãe | E6: Previdência privada (PGBL) | F6: Participações em empresas | G6: Empréstimo de pessoa física
A7: Funcionário(a) público(a) | B7: Nubank | C7: Avô(ó) | E7: Pensão alimentícia | F7: Outros bens e direitos | G7: Outras dívidas
A8: Profissional liberal | B8: Inter | C8: Irmão(ã) | E8: Doações incentivadas
A9: Sem ocupação | B9: C6 Bank | C9: Neto(a) | E9: Serviços de profissionais
A10: Outro | B10: Outro | C10: Outro | E10: Outros pagamentos

Sheet Menu
A1: 🧾 Organizador — Declaração de Imposto de Renda
A2: Reúna, organize e valide todas as informações antes de preencher o programa oficial da Receita Federal. Preencha as células amarelas de cada aba.
A4: Ano-calendário da declaração: | B4: 2026
A6: MENU DE NAVEGAÇÃO — clique no nome da aba para ir direto a ela
A7: ▶ 1 · Contribuinte | B7: Dados pessoais, contato e conta bancária para restituição.
A8: ▶ 2 · Dependentes | B8: Dependentes e alimentandos: nome, CPF, nascimento e parentesco.
A9: ▶ 3 · Rendimentos | B9: Fontes pagadoras e valores recebidos (tributáveis, isentos e exclusivos).
A10: ▶ 4 · Pagamentos | B10: Despesas dedutíveis: saúde, educação, previdência, pensão e outros.
A11: ▶ 5 · Bens e Direitos | B11: Imóveis, veículos, contas e investimentos em 31/12.
A12: ▶ 6 · Dívidas e Ônus | B12: Empréstimos e financiamentos em aberto em 31/12.
A13: ▶ 7 · Resumo | B13: Totais automáticos e checklist de conferência antes de declarar.
A15: LINKS RÁPIDOS — SITES OFICIAIS
A16: 🔗 Meu Imposto de Renda (Receita Federal)
A17: 🔗 Portal e-CAC (extrato da declaração, pendências e malha)
A18: 🔗 Baixar o programa oficial do IRPF
A19: 🔗 Consultar a restituição
A21: COMO USAR
A22: 1. Comece pela aba Contribuinte e siga a ordem do menu.
A23: 2. Campos com * são essenciais. Células amarelas são os campos de preenchimento.
A24: 3. Listas suspensas, datas e valores são validados automaticamente — se algo estiver fora do padrão, o Excel avisa na hora.
A25: 4. Campos obrigatórios esquecidos ficam destacados em vermelho na aba Contribuinte, e a aba Resumo mostra um checklist automático do que ainda falta.
A26: 5. Ao terminar, confira os totais na aba Resumo e transcreva os dados para o programa oficial.
A28: CHECKLIST RÁPIDO DE DOCUMENTOS
... A34: ☐ Declaração do ano anterior (arquivo .dec ou PDF), se houver

Sheet Contribuinte
A1: ◀ Voltar ao Menu
A2: Dados do Contribuinte (* = essencial)
A4: Nome completo * | C4: Conforme o CPF.
A5: CPF * | C5: 11 dígitos — com ou sem pontuação.
A6: Data de nascimento * | C6: Formato dd/mm/aaaa.
A7: Título de eleitor | C7: Opcional.
A8: Ocupação principal | C8: Escolha na lista.
A9: Endereço completo | C9: Rua, número, bairro, cidade/UF e CEP.
A10: E-mail | C10: Usado pela Receita para avisos.
A11: Telefone / celular | C11: Com DDD.
A12: Banco (restituição) | C12: Escolha na lista.
A13: Agência | C13: Sem o dígito, se houver campo separado.
A14: Conta (com dígito) | C14: Conta para crédito da restituição.
A15: Nome do cônjuge/companheiro(a) | C15: Se aplicável.
A16: CPF do cônjuge | C16: 11 dígitos — com ou sem pontuação.
A18: Dica: campos essenciais vazios ficam em vermelho até serem preenchidos.

Sheet Dependentes
A1: ◀ Voltar ao Menu
A2: Dependentes e Alimentandos
A3: Um dependente por linha. O CPF é obrigatório para todos os dependentes.
A4: Nome completo * | B4: CPF * | C4: Data de nascimento * | D4: Parentesco * | E4: Observações
A36: Total de dependentes informados: | B36: =COUNTA(A5:A34) -> 0

Sheet Rendimentos
A1: ◀ Voltar ao Menu
A2: Rendimentos — Fontes Pagadoras
A3: Uma linha por fonte pagadora, conforme o informe de rendimentos. Classifique o tipo: tributável, isento ou de tributação exclusiva.
A4: Tipo * | B4: Fonte pagadora * | C4: CNPJ/CPF da fonte * | D4: Valor recebido (R$) * | E4: Imposto retido — IRRF (R$) | F4: 13º salário (R$) | G4: Observações
A55: TOTAL | D55: =SUM(D5:D54) -> 0 | E55: =SUM(E5:E54) -> 0 | F55: =SUM(F5:F54) -> 0

Sheet Pagamentos
A1: ◀ Voltar ao Menu
A2: Pagamentos e Despesas Dedutíveis
A3: Registre as despesas que podem reduzir o imposto. O valor dedutível é calculado automaticamente (valor pago − reembolso).
A4: Categoria * | B4: Beneficiário / recebedor * | C4: CNPJ/CPF * | D4: Valor pago (R$) * | E4: Valor reembolsado (R$) | F4: Valor dedutível (R$) — automático | G4: Observações
F5: =MAX(D5-E5,0) -> 0
F6: =MAX(D6-E6,0) -> 0
F7: =MAX(D7-E7,0) -> 0
F8: =MAX(D8-E8,0) -> 0
F9: =MAX(D9-E9,0) -> 0
F10: =MAX(D10-E10,0) -> 0
F11: =MAX(D11-E11,0) -> 0
F12: =MAX(D12-E12,0) -> 0
F13: =MAX(D13-E13,0) -> 0
F14: =MAX(D14-E14,0) -> 0
F15: =MAX(D15-E15,0) -> 0
F16: =MAX(D16-E16,0) -> 0
... F54: =MAX(D54-E54,0) -> 0
A55: TOTAL | D55: =SUM(D5:D54) -> 0 | E55: =SUM(E5:E54) -> 0 | F55: =SUM(F5:F54) -> 0

Sheet Bens e Direitos
A1: ◀ Voltar ao Menu
A2: Bens e Direitos
A3: Informe a posição em 31/12 do ano anterior e em 31/12 do ano-calendário. A variação é automática.
A4: Grupo * | B4: Descrição * | C4: Valor em 31/12 ano anterior (R$) | D4: Valor em 31/12 ano atual (R$) | E4: Variação (R$) — automático
E5: =D5-C5 -> 0
E6: =D6-C6 -> 0
E7: =D7-C7 -> 0
E8: =D8-C8 -> 0
E9: =D9-C9 -> 0
E10: =D10-C10 -> 0
E11: =D11-C11 -> 0
E12: =D12-C12 -> 0
E13: =D13-C13 -> 0
E14: =D14-C14 -> 0
E15: =D15-C15 -> 0
E16: =D16-C16 -> 0
... E54: =D54-C54 -> 0
A55: TOTAL | C55: =SUM(C5:C54) -> 0 | D55: =SUM(D5:D54) -> 0 | E55: =SUM(E5:E54) -> 0

Sheet Dívidas e Ônus
A1: ◀ Voltar ao Menu
A2: Dívidas e Ônus Reais
A3: Empréstimos e financiamentos em aberto. Não inclua dívidas de valor igual ou inferior a R$ 5.000,00 (dispensadas pela Receita).
A4: Credor * | B4: Tipo * | C4: Saldo em 31/12 ano anterior (R$) | D4: Saldo em 31/12 ano atual (R$) | E4: Variação (R$) — automático
E5: =D5-C5 -> 0
E6: =D6-C6 -> 0
E7: =D7-C7 -> 0
E8: =D8-C8 -> 0
E9: =D9-C9 -> 0
E10: =D10-C10 -> 0
E11: =D11-C11 -> 0
E12: =D12-C12 -> 0
E13: =D13-C13 -> 0
E14: =D14-C14 -> 0
E15: =D15-C15 -> 0
E16: =D16-C16 -> 0
... E54: =D54-C54 -> 0
A55: TOTAL | C55: =SUM(C5:C54) -> 0 | D55: =SUM(D5:D54) -> 0 | E55: =SUM(E5:E54) -> 0

Sheet Resumo
A1: ◀ Voltar ao Menu
A2: Resumo e Conferência Automática
A4: TOTAIS DE RENDIMENTOS
A5: Rendimentos tributáveis | B5: =SUMIF(Rendimentos!A5:A54,"Tributável",Rendimentos!D5:D54) -> 0
A6: Rendimentos isentos e não tributáveis | B6: =SUMIF(Rendimentos!A5:A54,"Isento e não tributável",Rendimentos!D5:D54) -> 0
A7: Rendimentos de tributação exclusiva/definitiva | B7: =SUMIF(Rendimentos!A5:A54,"Tributação exclusiva/definitiva",Rendimentos!D5:D54) -> 0
A8: Imposto retido na fonte (IRRF) — total | B8: =SUM(Rendimentos!E5:E54) -> 0
A9: 13º salário — total | B9: =SUM(Rendimentos!F5:F54) -> 0
A10: Dependentes informados | B10: =COUNTA(Dependentes!A5:A34) -> 0
A12: DEDUÇÕES (PAGAMENTOS) — POR CATEGORIA
A13: Despesas médicas | B13: =SUMIF(Pagamentos!A5:A54,"Despesas médicas",Pagamentos!F5:F54) -> 0
A14: Plano de saúde | B14: =SUMIF(Pagamentos!A5:A54,"Plano de saúde",Pagamentos!F5:F54) -> 0
A15: Educação | B15: =SUMIF(Pagamentos!A5:A54,"Educação",Pagamentos!F5:F54) -> 0
A16: Previdência oficial (INSS) | B16: =SUMIF(Pagamentos!A5:A54,"Previdência oficial (INSS)",Pagamentos!F5:F54) -> 0
A17: Previdência privada (PGBL) | B17: =SUMIF(Pagamentos!A5:A54,"Previdência privada (PGBL)",Pagamentos!F5:F54) -> 0
A18: Pensão alimentícia | B18: =SUMIF(Pagamentos!A5:A54,"Pensão alimentícia",Pagamentos!F5:F54) -> 0
A19: Doações incentivadas | B19: =SUMIF(Pagamentos!A5:A54,"Doações incentivadas",Pagamentos!F5:F54) -> 0
A20: Serviços de profissionais | B20: =SUMIF(Pagamentos!A5:A54,"Serviços de profissionais",Pagamentos!F5:F54) -> 0
A21: Outros pagamentos | B21: =SUMIF(Pagamentos!A5:A54,"Outros pagamentos",Pagamentos!F5:F54) -> 0
A22: TOTAL DE DEDUÇÕES REGISTRADAS | B22: =SUM(Pagamentos!F5:F54) -> 0 | C22: Atenção: nem todo pagamento é dedutível sem limites — educação e previdência têm tetos legais.
A24: PATRIMÔNIO EM 31/12 DO ANO ATUAL
A25: Total de bens e direitos | B25: =SUM('Bens e Direitos'!D5:D54) -> 0
A26: Total de dívidas e ônus | B26: =SUM('Dívidas e Ônus'!D5:D54) -> 0
A28: CHECKLIST AUTOMÁTICO — O QUE AINDA FALTA
A29: Nome do contribuinte preenchido | B29: =IF(LEN(TRIM(Contribuinte!B4))>0,"✔ OK","❌ Pendente — aba Contribuinte") -> ❌ Pendente — aba Contribuinte
A30: CPF do contribuinte preenchido | B30: =IF(LEN(TRIM(Contribuinte!B5))>0,"✔ OK","❌ Pendente — aba Contribuinte") -> ❌ Pendente — aba Contribuinte
A31: Data de nascimento preenchida | B31: =IF(LEN(TRIM(Contribuinte!B6))>0,"✔ OK","❌ Pendente — aba Contribuinte") -> ❌ Pendente — aba Contribuinte
A32: Pelo menos uma fonte de rendimento informada | B32: =IF(COUNTA(Rendimentos!B5:B54)>0,"✔ OK","❌ Pendente — aba Rendimentos") -> ❌ Pendente — aba Rendimentos
A33: CPFs de todos os dependentes preenchidos | B33: =IF(COUNTA(Dependentes!A5:A34)=COUNTA(Dependentes!B5:B34),"✔ OK","❌ Verifique — aba Dependentes") -> ✔ OK
A34: Fontes com CNPJ/CPF informados | B34: =IF(COUNTA(Rendimentos!B5:B54)=COUNTA(Rendimentos!C5:C54),"✔ OK","❌ Verifique — aba Rendimentos") -> ✔ OK
A36: Observação: esta ferramenta organiza e confere os dados para a declaração. Ela não substitui o programa oficial da Receita Federal, onde o imposto é calculado e a declaração é transmitida.
